daudio/__init__.py
daudio/diarize.py
daudio/dnsmos.py
daudio/model.py
daudio/asr/__init__.py
daudio/asr/infer.py
daudio/asr/aliasr/__init__.py
daudio/asr/aliasr/info.py
daudio/asr/aliasr/auto/__init__.py
daudio/asr/aliasr/auto/auto_model.py
daudio/asr/aliasr/frontends/__init__.py
daudio/asr/aliasr/frontends/wav_frontend.py
daudio/asr/aliasr/frontends/utils/__init__.py
daudio/asr/aliasr/frontends/utils/beamformer.py
daudio/asr/aliasr/frontends/utils/dnn_beamformer.py
daudio/asr/aliasr/frontends/utils/dnn_wpe.py
daudio/asr/aliasr/frontends/utils/frontend.py
daudio/asr/aliasr/frontends/utils/log_mel.py
daudio/asr/aliasr/frontends/utils/mask_estimator.py
daudio/asr/aliasr/models/__init__.py
daudio/asr/aliasr/models/ctc/__init__.py
daudio/asr/aliasr/models/ctc/ctc.py
daudio/asr/aliasr/models/sense_voice/__init__.py
daudio/asr/aliasr/models/sense_voice/model.py
daudio/asr/aliasr/models/specaug/__init__.py
daudio/asr/aliasr/models/specaug/mask_along_axis.py
daudio/asr/aliasr/models/specaug/specaug.py
daudio/asr/aliasr/models/specaug/time_warp.py
daudio/asr/aliasr/tokenizer/__init__.py
daudio/asr/aliasr/tokenizer/abs_tokenizer.py
daudio/asr/aliasr/tokenizer/sentencepiece_tokenizer.py
daudio/asr/aliasr/train_utils/__init__.py
daudio/asr/aliasr/train_utils/load_pretrained_model.py
daudio/asr/aliasr/train_utils/set_all_random_seed.py
daudio/asr/aliasr/utils/__init__.py
daudio/asr/aliasr/utils/load_utils.py
daudio/asr/aliasr/utils/misc.py
daudio/asr/aliasr/utils/postprocess_utils.py
daudio/asr/aliasr/utils/torch_function.py
daudio-1.0.7.dist-info/METADATA
daudio-1.0.7.dist-info/WHEEL
daudio-1.0.7.dist-info/top_level.txt
daudio-1.0.7.dist-info/RECORD
